booklet_splitter/__init__.py
booklet_splitter-0.0.2.data/scripts/booklets
booklet_splitter-0.0.2.dist-info/LICENSE
booklet_splitter-0.0.2.dist-info/METADATA
booklet_splitter-0.0.2.dist-info/WHEEL
booklet_splitter-0.0.2.dist-info/top_level.txt
booklet_splitter-0.0.2.dist-info/RECORD
